kgw/__init__.py
kgw/_shared/__init__.py
kgw/_shared/base.py
kgw/_shared/extract.py
kgw/_shared/load.py
kgw/_shared/tasks.py
kgw/_shared/transform.py
kgw/biomedicine/__init__.py
kgw/biomedicine/_ckg.py
kgw/biomedicine/_hald.py
kgw/biomedicine/_hetionet.py
kgw/biomedicine/_monarchkg.py
kgw/biomedicine/_oregano.py
kgw/biomedicine/_primekg.py
tests/__init__.py
tests/conftest.py
tests/test_shared.py
tests/test_workflows.py
tests/utils.py
kgw-0.2.0.dist-info/LICENSE
kgw-0.2.0.dist-info/METADATA
kgw-0.2.0.dist-info/NOTICE
kgw-0.2.0.dist-info/WHEEL
kgw-0.2.0.dist-info/top_level.txt
kgw-0.2.0.dist-info/RECORD
