Metadata-Version: 2.1
Name: kgw
Version: 0.2.0
Summary: Knowledge Graph Workflows
Home-page: https://github.com/robert-haas/kgw
Author: Robert Haas
Author-email: robert.haas@protonmail.com
License: Apache License, Version 2.0
Classifier: Development Status :: 4 - Beta
Classifier: Intended Audience :: Science/Research
Classifier: License :: OSI Approved :: Apache Software License
Classifier: Natural Language :: English
Classifier: Operating System :: OS Independent
Classifier: Programming Language :: Python :: 3
Classifier: Topic :: Scientific/Engineering
Requires-Python: >=3.6
License-File: LICENSE
License-File: NOTICE
Requires-Dist: bs4
Requires-Dist: gravis
Requires-Dist: luigi
Requires-Dist: networkx
Requires-Dist: orjson
Requires-Dist: requests
